ascii_train.py
ascii_train-0.0.5.dist-info/METADATA
ascii_train-0.0.5.dist-info/RECORD
ascii_train-0.0.5.dist-info/WHEEL
ascii_train-0.0.5.dist-info/entry_points.txt
ascii_train-0.0.5.dist-info/top_level.txt
