Metadata-Version: 2.1
Name: ascii-train
Version: 0.0.5
Summary: Print an ascii train!
Home-page: https://github.com/noahp/ascii-train
Author: Noah Pendleton
Author-email: 2538614+noahp@users.noreply.github.com
License: UNKNOWN
Platform: UNKNOWN
Provides-Extra: test
Provides-Extra: test
Requires-Dist: pytest (>=3.5.1); extra == 'test'
Requires-Dist: pytest-cov (>=2.5.1); extra == 'test'
